pipen/__init__.py
pipen/__main__.py
pipen/_job_caching.py
pipen/channel.py
pipen/cli/__init__.py
pipen/cli/_hooks.py
pipen/cli/_main.py
pipen/cli/help.py
pipen/cli/plugins.py
pipen/cli/profile.py
pipen/cli/version.py
pipen/defaults.py
pipen/exceptions.py
pipen/job.py
pipen/pipen.py
pipen/pluginmgr.py
pipen/proc.py
pipen/procgroup.py
pipen/progressbar.py
pipen/py.typed
pipen/scheduler.py
pipen/template.py
pipen/utils.py
pipen/version.py
pipen-1.1.8.dist-info/METADATA
pipen-1.1.8.dist-info/WHEEL
pipen-1.1.8.dist-info/entry_points.txt
pipen-1.1.8.dist-info/licenses/LICENSE
pipen-1.1.8.dist-info/RECORD
