Metadata-Version: 2.4
Name: pipen
Version: 1.1.8
Summary: A pipeline framework for python
License: MIT
License-File: LICENSE
Author: pwwang
Author-email: pwwang@pwwang.com
Requires-Python: >=3.9,<4.0
Classifier: License :: OSI Approved :: MIT License
Classifier: Programming Language :: Python :: 3
Classifier: Programming Language :: Python :: 3.9
Classifier: Programming Language :: Python :: 3.10
Classifier: Programming Language :: Python :: 3.11
Classifier: Programming Language :: Python :: 3.12
Classifier: Programming Language :: Python :: 3.13
Classifier: Programming Language :: Python :: 3.14
Requires-Dist: argx (>=0.4,<0.5)
Requires-Dist: enlighten (>=1,<2)
Requires-Dist: liquidpy (>=0.8,<0.9)
Requires-Dist: pandas (>=2.0,<3.0)
Requires-Dist: pipda (>=0.13,<0.14)
Requires-Dist: python-simpleconf[toml] (>=0.8,<0.9)
Requires-Dist: varname (>=0.15,<0.16)
Requires-Dist: xqute (>=2.0,<3.0)
Project-URL: Homepage, https://github.com/pwwang/pipen
Project-URL: Repository, https://github.com/pwwang/pipen
